gptui/.default_config.yml
gptui/__init__.py
gptui/__main__.py
gptui/_version.py
gptui/config.yml
gptui/help.md
gptui/controllers/__init__.py
gptui/controllers/ai_care_sensors.py
gptui/controllers/assistant_tube_control.py
gptui/controllers/chat_context_control.py
gptui/controllers/chat_response_control.py
gptui/controllers/dash_board_control.py
gptui/controllers/decorate_display_control.py
gptui/controllers/group_talk_control.py
gptui/controllers/notification_control.py
gptui/controllers/openai_chat_manage.py
gptui/controllers/tube_files_control.py
gptui/controllers/voice_control.py
gptui/data/__init__.py
gptui/data/langchain/__init__.py
gptui/data/langchain/text_splitter.py
gptui/data/langchain/docstore/__init__.py
gptui/data/langchain/docstore/document.py
gptui/data/langchain/document_loaders/__init__.py
gptui/data/langchain/document_loaders/base.py
gptui/data/langchain/document_loaders/helpers.py
gptui/data/langchain/document_loaders/html.py
gptui/data/langchain/document_loaders/html_bs.py
gptui/data/langchain/document_loaders/text.py
gptui/data/langchain/document_loaders/unstructured.py
gptui/data/langchain/document_loaders/blob_loaders/__init__.py
gptui/data/langchain/document_loaders/blob_loaders/file_system.py
gptui/data/langchain/document_loaders/blob_loaders/schema.py
gptui/data/langchain/load/__init__.py
gptui/data/langchain/load/serializable.py
gptui/data/langchain/pydantic_v1/__init__.py
gptui/data/langchain/schema/__init__.py
gptui/data/langchain/schema/document.py
gptui/data/vector_memory/__init__.py
gptui/data/vector_memory/qdrant_memory.py
gptui/drivers/__init__.py
gptui/drivers/driver_error.py
gptui/drivers/driver_interface.py
gptui/drivers/driver_manager.py
gptui/drivers/drivers.py
gptui/gptui_kernel/__init__.py
gptui/gptui_kernel/kernel.py
gptui/gptui_kernel/kernel_exceptions.py
gptui/gptui_kernel/manager.py
gptui/gptui_kernel/manager_exceptions.py
gptui/gptui_kernel/null_logger.py
gptui/models/__init__.py
gptui/models/blinker_wrapper.py
gptui-0.5.4.dist-info/LICENSE
gptui-0.5.4.dist-info/METADATA
gptui-0.5.4.dist-info/WHEEL
gptui-0.5.4.dist-info/entry_points.txt
gptui-0.5.4.dist-info/top_level.txt
gptui-0.5.4.dist-info/RECORD
