Metadata-Version: 2.1
Name: gptui
Version: 0.5.4
Summary: A GPT conversational TUI tool that runs within the terminal.
Author-email: Xueao Chao <chaoxueao@gmail.com>
License: MIT License
Project-URL: Homepage, https://github.com/happyapplehorse/gptui
Project-URL: Bug Tracker, https://github.com/happyapplehorse/gptui/issues
Keywords: TUI,terminal,GPT,CLI,textual user interface
Classifier: Development Status :: 3 - Alpha
Classifier: Environment :: Console
Classifier: Intended Audience :: Developers
Classifier: Topic :: Software Development
Classifier: Topic :: Terminals
Classifier: Topic :: Scientific/Engineering :: Artificial Intelligence
Classifier: License :: OSI Approved :: MIT License
Classifier: Programming Language :: Python :: 3
Classifier: Programming Language :: Python :: 3.11
Classifier: Programming Language :: Python :: 3.12
Classifier: Operating System :: OS Independent
Classifier: Operating System :: POSIX :: Linux
Classifier: Operating System :: MacOS :: MacOS X
Classifier: Operating System :: Microsoft :: Windows
Requires-Python: >=3.10
License-File: LICENSE
Requires-Dist: agere <1,>=0.1.3
Requires-Dist: ai-care <1,>=0.1.3
Requires-Dist: aiofiles <24,>=23.1.0
Requires-Dist: beautifulsoup4 <5,>=4.12.2
Requires-Dist: blinker <2,>=1.6.2
Requires-Dist: chardet <6,>=5.1.0
Requires-Dist: geocoder <2,>=1.38.1
Requires-Dist: httpx <1,>=0.24.1
Requires-Dist: lxml <6,>=4.9.3
Requires-Dist: openai <2,>=1.2.0
Requires-Dist: playsound <2,>=1.3.0
Requires-Dist: Pygments <3,>=2.15.1
Requires-Dist: pyperclip <2,>=1.8.2
Requires-Dist: python-dotenv <2,>=1.0.0
Requires-Dist: PyYAML <7,>=6.0.1
Requires-Dist: qdrant-client <2,>=1.4.0
Requires-Dist: rich <14,>=13.7.0
Requires-Dist: semantic-kernel <1,>=0.4.0.dev0
Requires-Dist: textual <1,>=0.37.1
Requires-Dist: tiktoken <1,>=0.4.0
Requires-Dist: unstructured <1,>=0.10.18
